dharma/__init__.py
dharma/__main__.py
dharma/__version__.py
dharma/dharma.py
dharma/settings.py
dharma/core/__init__.py
dharma/core/dharma.py
dharma/core/extensions.py
dharma/core/websocket.py
dharma/grammars/canvas2d.dg
dharma/grammars/common.dg
dharma/grammars/json.dg
dharma/grammars/svg.dg
dharma/grammars/test.dg
dharma/grammars/url.dg
dharma/grammars/wasm.dg
dharma/grammars/xss.dg
dharma/grammars/nodejs/buffer.dg
dharma/grammars/var/index.html
dharma-1.3.2.dist-info/LICENSE.txt
dharma-1.3.2.dist-info/METADATA
dharma-1.3.2.dist-info/WHEEL
dharma-1.3.2.dist-info/entry_points.txt
dharma-1.3.2.dist-info/top_level.txt
dharma-1.3.2.dist-info/RECORD
