Metadata-Version: 2.1
Name: dharma
Version: 1.3.2
Summary: Generation-based, context-free grammar fuzzer.
Home-page: https://github.com/MozillaSecurity/dharma
Author: Christoph Diehl
Author-email: cdiehl@mozilla.com
Maintainer: Mozilla Fuzzing Team
Maintainer-email: fuzzing@mozilla.com
License: MPL 2.0
Download-URL: https://github.com/MozillaSecurity/dharma/tarball/1.3.2
Project-URL: Bug Tracker, https://github.com/MozillaSecurity/dharma/issues
Keywords: fuzzer fuzzing security testing generator
Platform: UNKNOWN
Classifier: Topic :: Software Development :: Testing
Classifier: Topic :: Security
Classifier: Intended Audience :: Developers
Classifier: Operating System :: OS Independent
Classifier: Programming Language :: Python :: 3
Classifier: License :: OSI Approved :: Mozilla Public License 2.0 (MPL 2.0)
